fb_phoneauth/__init__.py
fb_phoneauth/admin.py
fb_phoneauth/apps.py
fb_phoneauth/auth_backends.py
fb_phoneauth/forms.py
fb_phoneauth/migrations/__init__.py
fb_phoneauth/models.py
fb_phoneauth/static/fb_phoneauth/main.js
fb_phoneauth/templates/fb_phoneauth/login.html
fb_phoneauth/templates/fb_phoneauth/partials/login_form.html
fb_phoneauth/tests.py
fb_phoneauth/urls.py
fb_phoneauth/views.py
django_fb_phoneauth-0.1.3.dist-info/WHEEL
django_fb_phoneauth-0.1.3.dist-info/METADATA
django_fb_phoneauth-0.1.3.dist-info/RECORD
